postql/__init__.py
postql/cli.py
postql/version.py
postql/core/__init__.py
postql/core/data_operations.py
postql/core/database_management.py
PostQL-1.0.3.dist-info/LICENSE.txt
PostQL-1.0.3.dist-info/METADATA
PostQL-1.0.3.dist-info/WHEEL
PostQL-1.0.3.dist-info/entry_points.txt
PostQL-1.0.3.dist-info/top_level.txt
PostQL-1.0.3.dist-info/RECORD
