Metadata-Version: 2.1
Name: PostQL
Version: 1.0.3
Summary: Python wrapper for Postgres
Home-page: https://github.com/abeltavares/postql
Author: Abel Tavares
Author-email: abelst9@gmail.com
License: BSD
Project-URL: Homepage, https://abeltavares.github.io/PostQL/
Project-URL: Repository, https://github.com/abeltavares/postql
Classifier: License :: OSI Approved :: MIT License
Classifier: Topic :: Software Development :: Libraries :: Python Modules
Classifier: Topic :: Utilities
Classifier: Topic :: Database
Classifier: Programming Language :: Python :: 3 :: Only
License-File: LICENSE.txt
Requires-Dist: psycopg2-binary
Requires-Dist: tabulate
Requires-Dist: prompt-toolkit
Requires-Dist: termcolor
Requires-Dist: boto3
Requires-Dist: openpyxl
Requires-Dist: pyarrow
